Metadata-Version: 2.1
Name: DeFiPie
Version: 0.0.1
Summary: DeFiPie
Home-page: http://github.com/icmoore/defipie
Author: icmoore
Author-email: defipy.devs@gmail.com
License: MIT
Platform: UNKNOWN
License-File: LICENSE.txt
